edutils/__init__.py
edutils/log.py
edutils/object_pool.py
edutils/tm.py
edutils/ut.py
edutils/dbs/__init__.py
edutils/dbs/mysql.py
edutils/dbs/sqlite.py
edutils-0.0.1.4.dist-info/LICENSE
edutils-0.0.1.4.dist-info/METADATA
edutils-0.0.1.4.dist-info/WHEEL
edutils-0.0.1.4.dist-info/top_level.txt
edutils-0.0.1.4.dist-info/RECORD
