Metadata-Version: 2.1
Name: edutils
Version: 0.0.1.4
Summary: A small utils for Personal use
Home-page: https://github.com/pypa/sampleproject
Author: endlessday3
Author-email: endlessday3@qq.com
License: UNKNOWN
Platform: UNKNOWN
Classifier: Programming Language :: Python :: 3
Classifier: License :: OSI Approved :: MIT License
Classifier: Operating System :: OS Independent
Requires-Dist: pymysql
